codex_autorunner/__init__.py
codex_autorunner/__main__.py
codex_autorunner/api.py
codex_autorunner/bootstrap.py
codex_autorunner/cli.py
codex_autorunner/codex_cli.py
codex_autorunner/codex_runner.py
codex_autorunner/discovery.py
codex_autorunner/housekeeping.py
codex_autorunner/manifest.py
codex_autorunner/plugin_api.py
codex_autorunner/server.py
codex_autorunner/agents/__init__.py
codex_autorunner/agents/base.py
codex_autorunner/agents/registry.py
codex_autorunner/agents/types.py
codex_autorunner/agents/codex/__init__.py
codex_autorunner/agents/codex/harness.py
codex_autorunner/agents/opencode/__init__.py
codex_autorunner/agents/opencode/agent_config.py
codex_autorunner/agents/opencode/client.py
codex_autorunner/agents/opencode/constants.py
codex_autorunner/agents/opencode/events.py
codex_autorunner/agents/opencode/harness.py
codex_autorunner/agents/opencode/logging.py
codex_autorunner/agents/opencode/run_prompt.py
codex_autorunner/agents/opencode/runtime.py
codex_autorunner/agents/opencode/supervisor.py
codex_autorunner/core/__init__.py
codex_autorunner/core/about_car.py
codex_autorunner/core/adapter_utils.py
codex_autorunner/core/app_server_ids.py
codex_autorunner/core/app_server_logging.py
codex_autorunner/core/app_server_prompts.py
codex_autorunner/core/app_server_threads.py
codex_autorunner/core/app_server_utils.py
codex_autorunner/core/archive.py
codex_autorunner/core/circuit_breaker.py
codex_autorunner/core/codex_runner.py
codex_autorunner/core/config.py
codex_autorunner/core/docs.py
codex_autorunner/core/drafts.py
codex_autorunner/core/engine.py
codex_autorunner/core/exceptions.py
codex_autorunner/core/git_utils.py
codex_autorunner/core/hub.py
codex_autorunner/core/injected_context.py
codex_autorunner/core/locks.py
codex_autorunner/core/logging_utils.py
codex_autorunner/core/notifications.py
codex_autorunner/core/optional_dependencies.py
codex_autorunner/core/patch_utils.py
codex_autorunner/core/path_utils.py
codex_autorunner/core/prompt.py
codex_autorunner-1.1.0.dist-info/licenses/LICENSE
codex_autorunner-1.1.0.dist-info/METADATA
codex_autorunner-1.1.0.dist-info/WHEEL
codex_autorunner-1.1.0.dist-info/entry_points.txt
codex_autorunner-1.1.0.dist-info/top_level.txt
codex_autorunner-1.1.0.dist-info/RECORD
