Metadata-Version: 2.4
Name: codex-autorunner
Version: 1.1.0
Summary: Codex autorunner CLI per DESIGN-V1
Author: Codex
License: MIT License
Project-URL: Homepage, https://github.com/Git-on-my-level/codex-autorunner
Project-URL: Repository, https://github.com/Git-on-my-level/codex-autorunner
Project-URL: Issues, https://github.com/Git-on-my-level/codex-autorunner/issues
Keywords: codex,automation,agent,cli,fastapi
Classifier: License :: OSI Approved :: MIT License
Classifier: Programming Language :: Python :: 3
Classifier: Programming Language :: Python :: 3 :: Only
Classifier: Operating System :: OS Independent
Requires-Python: >=3.9
License-File: LICENSE
Requires-Dist: typer>=0.9
Requires-Dist: click<8.2
Requires-Dist: pyyaml>=6.0
Requires-Dist: fastapi>=0.111
Requires-Dist: uvicorn[standard]>=0.30
Requires-Dist: ptyprocess>=0.7
Requires-Dist: python-multipart>=0.0.9
Requires-Dist: python-dotenv>=1.0
Requires-Dist: httpx>=0.27
Requires-Dist: tenacity>=8.0
Provides-Extra: dev
Requires-Dist: black==25.11.0; extra == "dev"
Requires-Dist: mypy>=1.10; extra == "dev"
Requires-Dist: pytest>=7.0; extra == "dev"
Requires-Dist: pytest-asyncio>=0.23; extra == "dev"
Requires-Dist: pytest-timeout>=2.0; extra == "dev"
Requires-Dist: ruff>=0.5.0; extra == "dev"
Requires-Dist: types-PyYAML; extra == "dev"
Provides-Extra: telegram
Requires-Dist: httpx>=0.27; extra == "telegram"
Provides-Extra: voice
Requires-Dist: httpx>=0.27; extra == "voice"
Requires-Dist: python-multipart>=0.0.9; extra == "voice"
Provides-Extra: github
Dynamic: license-file
